pyperf_why-0.1.0.dist-info/METADATA
pyperf_why-0.1.0.dist-info/WHEEL
pyperf_why-0.1.0.dist-info/licenses/LICENSE
pyperf_why/__init__.py
pyperf_why/_pyperf_why_core.cpython-313-darwin.so
pyperf_why/extractor.py
pyperf_why/formatter.py
pyperf_why/runtime.py
pyperf_why-0.1.0.dist-info/RECORD
