Metadata-Version: 2.4
Name: pyperf-why
Version: 0.1.0
Classifier: Development Status :: 3 - Alpha
Classifier: Intended Audience :: Developers
Classifier: License :: OSI Approved :: MIT License
Classifier: Programming Language :: Python :: 3.8
Classifier: Programming Language :: Python :: 3.9
Classifier: Programming Language :: Python :: 3.10
Classifier: Programming Language :: Python :: 3.11
Classifier: Programming Language :: Python :: 3.12
Classifier: Programming Language :: Python :: 3.13
Classifier: Programming Language :: Rust
Classifier: Topic :: Software Development :: Quality Assurance
License-File: LICENSE
Summary: Explain why Python code is slow, not just where
Keywords: performance,profiling,optimization,python,rust,analysis,diagnostic
Author-email: Jagadhiswaran Devaraj <jwaran78@gmail.com>
License: MIT
Requires-Python: >=3.8
Project-URL: Homepage, https://github.com/jagadhis/pyperf-why
Project-URL: Repository, https://github.com/jagadhis/pyperf-why
Project-URL: Issues, https://github.com/jagadhis/pyperf-why/issues
